sopel_managerbot/__init__.py
sopel_managerbot/plugin.py
sopel_managerbot-0.1.0.dist-info/licenses/COPYING
sopel_managerbot-0.1.0.dist-info/METADATA
sopel_managerbot-0.1.0.dist-info/WHEEL
sopel_managerbot-0.1.0.dist-info/entry_points.txt
sopel_managerbot-0.1.0.dist-info/top_level.txt
sopel_managerbot-0.1.0.dist-info/RECORD
