Metadata-Version: 2.4
Name: sopel-managerbot
Version: 0.1.0
Summary: "Manager-like" approval/denial responses for Sopel IRC bots.
Author-email: dgw <dgw@technobabbl.es>
License-Expression: EFL-2.0
Project-URL: Homepage, https://github.com/dgw/sopel-managerbot
Project-URL: Bug Tracker, https://github.com/dgw/sopel-managerbot/issues
Keywords: sopel,plugin,bot,irc
Platform: Linux x86, x86-64
Classifier: Intended Audience :: Developers
Classifier: Intended Audience :: System Administrators
Classifier: Topic :: Communications :: Chat :: Internet Relay Chat
Requires-Python: <4,>=3.8
License-File: COPYING
Requires-Dist: sopel>=8.0
Dynamic: license-file
